pytraced/__init__.py
pytraced/_config.py
pytraced/_formatter.py
pytraced/_levels.py
pytraced/_logger.py
pytraced/_record.py
pytraced/_sink.py
pytraced/_traceback.py
pytraced/py.typed
pytraced/colours/__init__.py
pytraced/colours/_colouriser.py
pytraced/colours/_colours.py
pytraced-0.1.1.dist-info/LICENSE.md
pytraced-0.1.1.dist-info/METADATA
pytraced-0.1.1.dist-info/WHEEL
pytraced-0.1.1.dist-info/top_level.txt
pytraced-0.1.1.dist-info/RECORD
