Metadata-Version: 2.1
Name: pytraced
Version: 0.1.1
Summary: A simple, lightweight, & extensible logging library for python
Author: Eris
Author-email: Eris <theferretdetective@gmail.com>
License: # GNU GENERAL PUBLIC LICENSE
Project-URL: Homepage, https://github.com/FerretDetective/pytraced
Project-URL: IssueTracker, https://github.com/FerretDetective/pytraced/issues
Classifier: Development Status :: 3 - Alpha
Classifier: Intended Audience :: Developers
Classifier: License :: OSI Approved :: GNU General Public License v3 (GPLv3)
Classifier: Operating System :: OS Independent
Classifier: Programming Language :: Python :: 3.10
Classifier: Programming Language :: Python :: 3.11
Requires-Python: <4,>=3.10
License-File: LICENSE.md
Requires-Dist: colorama (>=0.4.6)
Provides-Extra: dev
Requires-Dist: mypy (>=1.3.0) ; extra == 'dev'
Requires-Dist: types-colorama (==0.4.15.11) ; extra == 'dev'
Requires-Dist: pylint (>=2.17.4) ; extra == 'dev'
Requires-Dist: black (>=0.4.6) ; extra == 'dev'
Requires-Dist: tox (>=4.0.16) ; extra == 'dev'
Requires-Dist: pytest (>=7.3.2) ; extra == 'dev'
Requires-Dist: isort (>=5.12.0) ; extra == 'dev'
Requires-Dist: pytest-cov (>=4.1.0) ; extra == 'dev'
Requires-Dist: pympler (>=1.0.1) ; extra == 'dev'
